langevals_aws/comprehend_pii_detection.py
langevals_aws-0.1.7.dist-info/METADATA
langevals_aws-0.1.7.dist-info/WHEEL
langevals_aws-0.1.7.dist-info/RECORD
