Metadata-Version: 2.1
Name: langevals-aws
Version: 0.1.7
Summary: LangEvals integration for AWS APIs evaluators
License: MIT
Author: Rogerio Chaves
Author-email: rogerio@langwatch.ai
Requires-Python: >=3.11,<4.0
Classifier: License :: OSI Approved :: MIT License
Classifier: Programming Language :: Python :: 3
Classifier: Programming Language :: Python :: 3.11
Classifier: Programming Language :: Python :: 3.12
Classifier: Programming Language :: Python :: 3.13
Requires-Dist: boto3 (>=1.34.67,<2.0.0)
Requires-Dist: langevals-core (>=0.1.12,<0.2.0)
